{"plugins":
  [
    {"name":"QQ","url":"http://spirits.eu.org/music/qq.js"},
    {"name":"酷我","url":"http://spirits.eu.org/music/kuwo.js"},
    {"name":"酷狗","url":"http://spirits.eu.org/music/kugou.js"},
    {"name":"网易云","url":"http://spirits.eu.org/music/netease.js"},
    {"name":"咪咕","url":"http://spirits.eu.org/music/migu.js"},
    {"name":"千千","url":"http://spirits.eu.org/music/qianqian.js"},
    {"name":"全民K歌","url":"http://spirits.eu.org/music/qmkg.js"},
    {"name":"哔哩哔哩","url":"http://spirits.eu.org/music/bilibili.js"},
    {"name":"喜马拉雅","url":"http://spirits.eu.org/music/xmly.js"},
    {"name":"5sing","url":"http://spirits.eu.org/music/5sing.js"},
    {"name":"快手","url":"http://spirits.eu.org/music/kuaishou.js"},
    {"name":"猫耳","url":"http://spirits.eu.org/music/maoer.js"},
    {"name":"zz123","url":"http://spirits.eu.org/music/zz123.js"},
    {"name":"Global music","url":"http://spirits.eu.org/music/global.js"}
  ]
}
